MANIFEST.in
README.md
setup.cfg
setup.py
chord_labels/__init__.py
chord_labels/chord_labels.py
chord_labels.egg-info/PKG-INFO
chord_labels.egg-info/SOURCES.txt
chord_labels.egg-info/dependency_links.txt
chord_labels.egg-info/not-zip-safe
chord_labels.egg-info/requires.txt
chord_labels.egg-info/top_level.txt
chord_labels/parser/ChordLabel.tokens
chord_labels/parser/ChordLabelLexer.py
chord_labels/parser/ChordLabelLexer.tokens
chord_labels/parser/ChordLabelListener.py
chord_labels/parser/ChordLabelParser.py
chord_labels/parser/__init__.py